<?xml version="1.0" encoding="utf-8"?>
<!-- This is a CI serialization file for /Medical-center -->
<cms.node>
  <NodeACLID>
    <GUID>0072d163-58b7-495f-bbcd-1f15eaadf7e3</GUID>
    <ObjectType>cms.acl</ObjectType>
    <Site>
      <CodeName>MEDIOClinic</CodeName>
      <GUID>23f11601-ba95-4b71-8b02-e61f4984ada1</GUID>
      <ObjectType>cms.site</ObjectType>
    </Site>
  </NodeACLID>
  <NodeAlias>Medical-center</NodeAlias>
  <NodeClassID>
    <CodeName>MEDIO.MedicalCenter</CodeName>
    <GUID>ecabde25-db34-43ab-baf8-484b826df5e2</GUID>
    <ObjectType>cms.documenttype</ObjectType>
  </NodeClassID>
  <NodeGUID>da952d07-cf7a-46ca-a16a-e2992dcfbf07</NodeGUID>
  <NodeIsACLOwner>False</NodeIsACLOwner>
  <NodeName>Medical center</NodeName>
  <NodeOrder>2</NodeOrder>
  <NodeOwner>
    <CodeName>administrator</CodeName>
    <GUID>6415b8ce-8072-4bcd-8e48-9d7178b826b7</GUID>
    <ObjectType>cms.user</ObjectType>
  </NodeOwner>
  <NodeParentID>
    <CodeName>/</CodeName>
    <GUID>acdd2058-bde0-4c9d-8332-45f417220571</GUID>
    <ObjectType>cms.node</ObjectType>
    <Site>
      <CodeName>MEDIOClinic</CodeName>
      <GUID>23f11601-ba95-4b71-8b02-e61f4984ada1</GUID>
      <ObjectType>cms.site</ObjectType>
    </Site>
  </NodeParentID>
  <NodeSiteID>
    <CodeName>MEDIOClinic</CodeName>
    <GUID>23f11601-ba95-4b71-8b02-e61f4984ada1</GUID>
    <ObjectType>cms.site</ObjectType>
  </NodeSiteID>
</cms.node>