<?xml version="1.0" encoding="utf-8"?>
<cms.classpermission>
  <ClassID>
    <CodeName>MEDIO.MedicalCenter</CodeName>
    <GUID>ecabde25-db34-43ab-baf8-484b826df5e2</GUID>
    <ObjectType>cms.documenttype</ObjectType>
  </ClassID>
  <PermissionDescription>{$permissiondescription.document.destroy$}</PermissionDescription>
  <PermissionDisplayInMatrix>True</PermissionDisplayInMatrix>
  <PermissionDisplayName>{$permissionnames.destroy$}</PermissionDisplayName>
  <PermissionGUID>bcb5cda6-e5a9-498f-9736-34c03e6dd80e</PermissionGUID>
  <PermissionName>Destroy</PermissionName>
  <PermissionOrder>6</PermissionOrder>
</cms.classpermission>